digital_thought_commons/__init__.py
digital_thought_commons/version
digital_thought_commons/_resources/cache/default_cache_config.yaml
digital_thought_commons/_resources/elasticsearch/component_templates/custom-metadata-v1.json
digital_thought_commons/_resources/elasticsearch/component_templates/custom-metadata-v2.json
digital_thought_commons/_resources/elasticsearch/component_templates/event-message-v1.json
digital_thought_commons/_resources/elasticsearch/component_templates/ip-domain-detail-v1.json
digital_thought_commons/_resources/elasticsearch/component_templates/ip-domain-detail-v2.json
digital_thought_commons/_resources/elasticsearch/component_templates/url-detail-v1.json
digital_thought_commons/_resources/elasticsearch/component_templates/user-agent-v1.json
digital_thought_commons/_resources/elasticsearch/index_templates/api-cache-v1.json
digital_thought_commons/_resources/elasticsearch/index_templates/event-logs-v1.json
digital_thought_commons/_resources/elasticsearch/index_templates/exfiltrated-data-v1.json
digital_thought_commons/_resources/elasticsearch/index_templates/malicious-urls-v1.json
digital_thought_commons/_resources/elasticsearch/index_templates/o365-e3-audit-logs-v1.json
digital_thought_commons/_resources/elasticsearch/index_templates/velociraptor-rdp-v1.json
digital_thought_commons/_resources/elasticsearch/index_templates/zscaler-v1.json
digital_thought_commons/_resources/elasticsearch/index_templates/zscaler-v2.json
digital_thought_commons/_resources/elasticsearch/lifecycles/api-cache.json
digital_thought_commons/_resources/elasticsearch/lifecycles/logs.json
digital_thought_commons/_resources/elasticsearch/lifecycles/malicious-urls.json
digital_thought_commons/_resources/grok/aws
digital_thought_commons/_resources/grok/bacula
digital_thought_commons/_resources/grok/bind
digital_thought_commons/_resources/grok/bro
digital_thought_commons/_resources/grok/exim
digital_thought_commons/_resources/grok/firewalls
digital_thought_commons-1.0.2.dist-info/METADATA
digital_thought_commons-1.0.2.dist-info/WHEEL
digital_thought_commons-1.0.2.dist-info/entry_points.txt
digital_thought_commons-1.0.2.dist-info/top_level.txt
digital_thought_commons-1.0.2.dist-info/RECORD
