Metadata-Version: 2.1
Name: digital-thought-commons
Version: 1.0.2
Summary: My standard python libs for doing things
Home-page: https://github.com/Digital-Thought/commons
Author: Digital Thought
Author-email: development@digital-thought.org
License: UNKNOWN
Platform: UNKNOWN
Classifier: Programming Language :: Python :: 3.8
Classifier: Programming Language :: Python :: 3.9
Classifier: License :: OSI Approved :: GNU Affero General Public License v3
Classifier: Operating System :: OS Independent
Classifier: Development Status :: 4 - Beta
Requires-Python: >=3.8
Requires-Dist: requests (>=2.24.0)
Requires-Dist: PyYaml (>=5.3.1)
Requires-Dist: pytz (>=2020.1)
Requires-Dist: pytz-convert (>=0.2.9)
Requires-Dist: user-agents (>=2.2.0)
Requires-Dist: numpy (>=1.19.2)
Requires-Dist: pandas (>=1.1.3)
Requires-Dist: sklearn (~=0.0)
Requires-Dist: stringcase (>=1.2.0)
Requires-Dist: IPy (>=1.0)
Requires-Dist: colorlog (>=4.4.0)
Requires-Dist: beautifulsoup4 (>=4.9.3)
Requires-Dist: xlsxwriter (>=1.3.7)
Requires-Dist: geoip2 (>=4.1.0)
Requires-Dist: regex (==2015.10.29)
Requires-Dist: pysocks
Requires-Dist: urllib3 (>=1.26.5)
Requires-Dist: scikit-learn (~=0.23.2)
Requires-Dist: setuptools (~=50.3.2)
Requires-Dist: google-api-python-client
Requires-Dist: google-auth-httplib2
Requires-Dist: google-auth-oauthlib
Requires-Dist: selenium (==3.141.0)
Requires-Dist: elasticsearch
Requires-Dist: sqlalchemy
Requires-Dist: iso8601
Requires-Dist: xmltodict
